SuperIntelligence/__init__.py
SuperIntelligence/module.py
TikTok/__init__.py
TikTok/module.py
kwai/__init__.py
kwai/module.py
text2video/__init__.py
text2video/module.py
video/__init__.py
video/module.py
SuperIntelligence-0.0.1.dist-info/METADATA
SuperIntelligence-0.0.1.dist-info/WHEEL
SuperIntelligence-0.0.1.dist-info/top_level.txt
SuperIntelligence-0.0.1.dist-info/RECORD
